<car name_character="El Coronel" sprite_code="truck" max_speed="5.9" min_speed="2.5" aceleration="0.3" desaceleration="0.08" rotation_angle="0.32" avatar="avatar7" racer_image='car7'>
<!--NORMAL, NOACTION, RUN, FORWARD, REVERSE, DAMAGED, ERASE, YAW-->
    <animations>
        <animation name="normal" frames="0" delay="1"/>
        <animation name="noaction" frames="0" delay="1"/>
        <animation name="foward" frames="0" delay="1"/>
        <animation name="run" frames="0" delay="1"/>
        <animation name="reverse" frames="0" delay="1"/>
        <animation name="damaged" frames="0" delay="1"/>
        <animation name="erase" frames="0" delay="1"/>
        <animation name="yaw" frames="0" delay="1"/>
        <animation name="fall" frames="0" delay="1"/>
        <animation name="turbo" frames="0" delay="1"/>
    </animations>
</car>
